sigmaex/__init__.py
sigmaex/sigmaex.py
sigmaex-0.1.3.dist-info/LICENSE
sigmaex-0.1.3.dist-info/METADATA
sigmaex-0.1.3.dist-info/WHEEL
sigmaex-0.1.3.dist-info/entry_points.txt
sigmaex-0.1.3.dist-info/top_level.txt
sigmaex-0.1.3.dist-info/RECORD
