Metadata-Version: 2.1
Name: sigmaex
Version: 0.1.3
Summary: A python package for checking the gaussian histogram of data array.
Home-page: https://github.com/lmytime/sigmaex
Author: Mingyu Li
Author-email: lmytime@hotmail.com
License: GPL3
Classifier: Programming Language :: Python :: 3
Classifier: License :: OSI Approved :: GNU General Public License v3 (GPLv3)
Classifier: Operating System :: OS Independent
Requires-Python: >=3.6
License-File: LICENSE
Requires-Dist: numpy
Requires-Dist: scipy
Requires-Dist: astropy
Requires-Dist: tifffile
Requires-Dist: matplotlib
Requires-Dist: lmfit
